vekta_testa/__init__.py
vekta_testa/graph.py
vekta_testa/runner.py
vekta_testa/types.py
vekta_testa/utils.py
vecta_testa-0.1.1.dist-info/LICENSE
vecta_testa-0.1.1.dist-info/METADATA
vecta_testa-0.1.1.dist-info/WHEEL
vecta_testa-0.1.1.dist-info/top_level.txt
vecta_testa-0.1.1.dist-info/RECORD
