Metadata-Version: 2.1
Name: vecta-testa
Version: 0.1.1
Summary: A package for testing vector embeddings.
Home-page: https://github.com/Hint-Services/vekta-testa
Author: Hint Services
Author-email: ben@hint.services
License: MIT
Classifier: License :: OSI Approved :: MIT License
Classifier: Programming Language :: Python :: 3
License-File: LICENSE
